paintress_cli/__init__.py
paintress_cli/browser.py
paintress_cli/cli.py
paintress_cli/config.py
paintress_cli/display.py
paintress_cli/environment.py
paintress_cli/events.py
paintress_cli/hooks.py
paintress_cli/logging.py
paintress_cli/mcp.py
paintress_cli/processes.py
paintress_cli/runtime.py
paintress_cli/session.py
paintress_cli/usage.py
paintress_cli/app/__init__.py
paintress_cli/app/commands.py
paintress_cli/app/state.py
paintress_cli/app/tui.py
paintress_cli/hitl/__init__.py
paintress_cli/hitl/approval.py
paintress_cli/hitl/ui.py
paintress_cli/rendering/__init__.py
paintress_cli/rendering/event_renderer.py
paintress_cli/rendering/renderer.py
paintress_cli/rendering/tool_message.py
paintress_cli/rendering/tracker.py
paintress_cli/rendering/types.py
paintress_cli/rendering/tool_panels/__init__.py
paintress_cli/rendering/tool_panels/base.py
paintress_cli/rendering/tool_panels/edit_panel.py
paintress_cli/rendering/tool_panels/task_panel.py
paintress_cli/rendering/tool_panels/thinking_panel.py
paintress_cli/rendering/tool_panels/todo_panel.py
paintress_cli/skills/__init__.py
paintress_cli/skills/building-agents/README.md
paintress_cli/skills/building-agents/SKILL.md
paintress_cli/skills/building-agents/docs/README.md
paintress_cli/skills/building-agents/docs/context.md
paintress_cli/skills/building-agents/docs/environment.md
paintress_cli/skills/building-agents/docs/events.md
paintress_cli/skills/building-agents/docs/logging.md
paintress_cli/skills/building-agents/docs/message-bus.md
paintress_cli/skills/building-agents/docs/model.md
paintress_cli/skills/building-agents/docs/resumable-resources.md
paintress_cli/skills/building-agents/docs/skills.md
paintress_cli/skills/building-agents/docs/streaming.md
paintress_cli/skills/building-agents/docs/subagent.md
paintress_cli/skills/building-agents/docs/toolset.md
paintress_cli/skills/building-agents/examples/.env.example
paintress_cli/skills/building-agents/examples/__init__.py
paintress_cli-0.13.0.dist-info/METADATA
paintress_cli-0.13.0.dist-info/WHEEL
paintress_cli-0.13.0.dist-info/entry_points.txt
paintress_cli-0.13.0.dist-info/licenses/LICENSE
paintress_cli-0.13.0.dist-info/RECORD
