Metadata-Version: 2.4
Name: paintress-cli
Version: 0.13.0
Summary: TUI reference implementation for pai-agent-sdk
Project-URL: Repository, https://github.com/youware-labs/pai-agent-sdk
Author-email: youware <lab@youware.com>
License-File: LICENSE
Keywords: ai-agent,cli,python,tui
Classifier: Environment :: Console
Classifier: Intended Audience :: Developers
Classifier: Programming Language :: Python
Classifier: Programming Language :: Python :: 3
Classifier: Programming Language :: Python :: 3.11
Classifier: Programming Language :: Python :: 3.12
Classifier: Programming Language :: Python :: 3.13
Classifier: Topic :: Software Development :: Libraries :: Python Modules
Requires-Python: <3.14,>=3.11
Requires-Dist: agent-environment>=0.1.0
Requires-Dist: click>=8.0
Requires-Dist: pai-agent-sdk[all]==0.13.0
Requires-Dist: pydantic-ai
Requires-Dist: pydantic-settings>=2.0
Requires-Dist: pydantic>=2.0
